proj2/pwm.v
module pwm #(parameter PWM_CNT = 10)
	(
	    input clk,
	    input reset,
	    input [PWM_CNT-1:0] cmp,
	    output reg pwm
	);

	reg [PWM_CNT-1:0] cnt_a, cnt_b;
	reg pwm_out;
	
	always @(posedge clk) begin
		cnt_a = cnt_b + 1'b1;
	
	        if (cmp > cnt_b)
		    pwm <= 1'b1;
		else
		    pwm <= 1'b0;
	end
	
	always @(posedge clk) begin
	      if(reset == 1'b1) begin
		cnt_b <= 1'b0;
	     end
	     else begin
		cnt_b <= cnt_a;
	    end
	end

endmodule

proj2/toplevel_tb.v
`define DUMPSTR(x) `"x.vcd`"
`timescale 1 ns / 1 ps

module toplevel_tb();

parameter DURATION = 100000;
reg clk = 0;
reg rst = 0;
reg [9:0] cmp;
wire [1:0] out;

pwm UUT(
	.clk(clk),
	.reset(rst),
	.cmp(cmp),
	.pwm(out)
	);
initial begin

	$dumpfile(`DUMPSTR(`VCD_OUTPUT));
	$dumpvars(0,toplevel_tb);
	#(DURATION) $display("End of simulation");
	$finish;
end

initial begin
cmp = 9'b100000000;
#100;
rst = 1'b1;
#100;
rst = 1'b0;
#30000
cmp =10'b1011111000;
end

always begin
#1;
clk =~clk;
end
endmodule

proj2/toplevel_tb.vcd
$date
	Mon Feb 13 20:03:16 2023
$end
$version
	Icarus Verilog
$end
$timescale
	1ps
$end
$scope module toplevel_tb $end
$var wire 2 ! out [1:0] $end
$var reg 1 " clk $end
$var reg 10 # cmp [9:0] $end
$var reg 1 $ rst $end
$scope module UUT $end
$var wire 1 " clk $end
$var wire 10 % cmp [9:0] $end
$var wire 1 $ reset $end
$var reg 10 & cnt_a [9:0] $end
$var reg 10 ' cnt_b [9:0] $end
$var reg 1 ( pwm $end
$upscope $end
$upscope $end
$enddefinitions $end
#0
$dumpvars
x(
bx '
bx &
b100000000 %
0$
b100000000 #
0"
b0x !
$end
#1000
b0 !
0(
1"
#2000
0"
#3000
1"
#4000
0"
#5000
1"
#6000
0"
#7000
1"
#8000
0"
#9000
1"
#10000
0"
#11000
1"
#12000
0"
#13000
1"
#14000
0"
#15000
1"
#16000
0"
#17000
1"
#18000
0"
#19000
1"
#20000
0"
#21000
1"
#22000
0"
#23000
1"
#24000
0"
#25000
1"
#26000
0"
#27000
1"
#28000
0"
#29000
1"
#30000
0"
#31000
1"
#32000
0"
#33000
1"
#34000
0"
#35000
1"
#36000
0"
#37000
1"
#38000
0"
#39000
1"
#40000
0"
#41000
1"
#42000
0"
#43000
1"
#44000
0"
#45000
1"
#46000
0"
#47000
1"
#48000
0"
#49000
1"
#50000
0"
#51000
1"
#52000
0"
#53000
1"
#54000
0"
#55000
1"
#56000
0"
#57000
1"
#58000
0"
#59000
1"
#60000
0"
#61000
1"
#62000
0"
#63000
1"
#64000
0"
#65000
1"
#66000
0"
#67000
1"
#68000
0"
#69000
1"
#70000
0"
#71000
1"
#72000
0"
#73000
1"
#74000
0"
#75000
1"
#76000
0"
#77000
1"
#78000
0"
#79000
1"
#80000
0"
#81000
1"
#82000
0"
#83000
1"
#84000
0"
#85000
1"
#86000
0"
#87000
1"
#88000
0"
#89000
1"
#90000
0"
#91000
1"
#92000
0"
#93000
1"
#94000
0"
#95000
1"
#96000
0"
#97000
1"
#98000
0"
#99000
1"
#100000
0"
1$
#101000
b0 '
1"
#102000
0"
#103000
b1 !
1(
b1 &
1"
#104000
0"
#105000
1"
#106000
0"
#107000
1"
#108000
0"
#109000
1"
#110000
0"
#111000
1"
#112000
0"
#113000
1"
#114000
0"
#115000
1"
#116000
0"
#117000
1"
#118000
0"
#119000
1"
#120000
0"
#121000
1"
#122000
0"
#123000
1"
#124000
0"
#125000
1"
#126000
0"
#127000
1"
#128000
0"
#129000
1"
#130000
0"
#131000
1"
#132000
0"
#133000
1"
#134000
0"
#135000
1"
#136000
0"
#137000
1"
#138000
0"
#139000
1"
#140000
0"
#141000
1"
#142000
0"
#143000
1"
#144000
0"
#145000
1"
#146000
0"
#147000
1"
#148000
0"
#149000
1"
#150000
0"
#151000
1"
#152000
0"
#153000
1"
#154000
0"
#155000
1"
#156000
0"
#157000
1"
#158000
0"
#159000
1"
#160000
0"
#161000
1"
#162000
0"
#163000
1"
#164000
0"
#165000
1"
#166000
0"
#167000
1"
#168000
0"
#169000
1"
#170000
0"
#171000
1"
#172000
0"
#173000
1"
#174000
0"
#175000
1"
#176000
0"
#177000
1"
#178000
0"
#179000
1"
#180000
0"
#181000
1"
#182000
0"
#183000
1"
#184000
0"
#185000
1"
#186000
0"
#187000
1"
#188000
0"
#189000
1"
#190000
0"
#191000
1"
#192000
0"
#193000
1"
#194000
0"
#195000
1"
#196000
0"
#197000
1"
#198000
0"
#199000
1"
#200000
0"
0$
#201000
b1 '
1"
#202000
0"
#203000
b10 '
b10 &
1"
#204000
0"
#205000
b11 &
1"
#206000
0"
#207000
b11 '
1"
#208000
0"
#209000
b100 &
1"
#210000
0"
#211000
b100 '
1"
#212000
0"
#213000
b101 &
1"
#214000
0"
#215000
b101 '
1"
#216000
0"
#217000
b110 &
1"
#218000
0"
#219000
b110 '
1"
#220000
0"
#221000
b111 &
1"
#222000
0"
#223000
b111 '
1"
#224000
0"
#225000
b1000 &
1"
#226000
0"
#227000
b1000 '
1"
#228000
0"
#229000
b1001 &
1"
#230000
0"
#231000
b1001 '
1"
#232000
0"
#233000
b1010 &
1"
#234000
0"
#235000
b1010 '
1"
#236000
0"
#237000
b1011 &
1"
#238000
0"
#239000
b1011 '
1"
#240000
0"
#241000
b1100 &
1"
#242000
0"
#243000
b1100 '
1"
#244000
0"
#245000
b1101 &
1"
#246000
0"
#247000
b1101 '
1"
#248000
0"
#249000
b1110 &
1"
#250000
0"
#251000
b1110 '
1"
#252000
0"
#253000
b1111 &
1"
#254000
0"
#255000
b1111 '
1"
#256000
0"
#257000
b10000 &
1"
#258000
0"
#259000
b10000 '
1"
#260000
0"
#261000
b10001 &
1"
#262000
0"
#263000
b10001 '
1"
#264000
0"
#265000
b10010 &
1"
#266000
0"
#267000
b10010 '
1"
#268000
0"
#269000
b10011 &
1"
#270000
0"
#271000
b10011 '
1"
#272000
0"
#273000
b10100 &
1"
#274000
0"
#275000
b10100 '
1"
#276000
0"
#277000
b10101 &
1"
#278000
0"
#279000
b10101 '
1"
#280000
0"
#281000
b10110 &
1"
#282000
0"
#283000
b10110 '
1"
#284000
0"
#285000
b10111 &
1"
#286000
0"
#287000
b10111 '
1"
#288000
0"
#289000
b11000 &
1"
#290000
0"
#291000
b11000 '
1"
#292000
0"
#293000
b11001 &
1"
#294000
0"
#295000
b11001 '
1"
#296000
0"
#297000
b11010 &
1"
#298000
0"
#299000
b11010 '
1"
#300000
0"
#301000
b11011 &
1"
#302000
0"
#303000
b11011 '
1"
#304000
0"
#305000
b11100 &
1"
#306000
0"
#307000
b11100 '
1"
#308000
0"
#309000
b11101 &
1"
#310000
0"
#311000
b11101 '
1"
#312000
0"
#313000
b11110 &
1"
#314000
0"
#315000
b11110 '
1"
#316000
0"
#317000
b11111 &
1"
#318000
0"
#319000
b11111 '
1"
#320000
0"
#321000
b100000 &
1"
#322000
0"
#323000
b100000 '
1"
#324000
0"
#325000
b100001 &
1"
#326000
0"
#327000
b100001 '
1"
#328000
0"
#329000
b100010 &
1"
#330000
0"
#331000
b100010 '
1"
#332000
0"
#333000
b100011 &
1"
#334000
0"
#335000
b100011 '
1"
#336000
0"
#337000
b100100 &
1"
#338000
0"
#339000
b100100 '
1"
#340000
0"
#341000
b100101 &
1"
#342000
0"
#343000
b100101 '
1"
#344000
0"
#345000
b100110 &
1"
#346000
0"
#347000
b100110 '
1"
#348000
0"
#349000
b100111 &
1"
#350000
0"
#351000
b100111 '
1"
#352000
0"
#353000
b101000 &
1"
#354000
0"
#355000
b101000 '
1"
#356000
0"
#357000
b101001 &
1"
#358000
0"
#359000
b101001 '
1"
#360000
0"
#361000
b101010 &
1"
#362000
0"
#363000
b101010 '
1"
#364000
0"
#365000
b101011 &
1"
#366000
0"
#367000
b101011 '
1"
#368000
0"
#369000
b101100 &
1"
#370000
0"
#371000
b101100 '
1"
#372000
0"
#373000
b101101 &
1"
#374000
0"
#375000
b101101 '
1"
#376000
0"
#377000
b101110 &
1"
#378000
0"
#379000
b101110 '
1"
#380000
0"
#381000
b101111 &
1"
#382000
0"
#383000
b101111 '
1"
#384000
0"
#385000
b110000 &
1"
#386000
0"
#387000
b110000 '
1"
#388000
0"
#389000
b110001 &
1"
#390000
0"
#391000
b110001 '
1"
#392000
0"
#393000
b110010 &
1"
#394000
0"
#395000
b110010 '
1"
#396000
0"
#397000
b110011 &
1"
#398000
0"
#399000
b110011 '
1"
#400000
0"
#401000
b110100 &
1"
#402000
0"
#403000
b110100 '
1"
#404000
0"
#405000
b110101 &
1"
#406000
0"
#407000
b110101 '
1"
#408000
0"
#409000
b110110 &
1"
#410000
0"
#411000
b110110 '
1"
#412000
0"
#413000
b110111 &
1"
#414000
0"
#415000
b110111 '
1"
#416000
0"
#417000
b111000 &
1"
#418000
0"
#419000
b111000 '
1"
#420000
0"
#421000
b111001 &
1"
#422000
0"
#423000
b111001 '
1"
#424000
0"
#425000
b111010 &
1"
#426000
0"
#427000
b111010 '
1"
#428000
0"
#429000
b111011 &
1"
#430000
0"
#431000
b111011 '
1"
#432000
0"
#433000
b111100 &
1"
#434000
0"
#435000
b111100 '
1"
#436000
0"
#437000
b111101 &
1"
#438000
0"
#439000
b111101 '
1"
#440000
0"
#441000
b111110 &
1"
#442000
0"
#443000
b111110 '
1"
#444000
0"
#445000
b111111 &
1"
#446000
0"
#447000
b111111 '
1"
#448000
0"
#449000
b1000000 &
1"
#450000
0"
#451000
b1000000 '
1"
#452000
0"
#453000
b1000001 &
1"
#454000
0"
#455000
b1000001 '
1"
#456000
0"
#457000
b1000010 &
1"
#458000
0"
#459000
b1000010 '
1"
#460000
0"
#461000
b1000011 &
1"
#462000
0"
#463000
b1000011 '
1"
#464000
0"
#465000
b1000100 &
1"
#466000
0"
#467000
b1000100 '
1"
#468000
0"
#469000
b1000101 &
1"
#470000
0"
#471000
b1000101 '
1"
#472000
0"
#473000
b1000110 &
1"
#474000
0"
#475000
b1000110 '
1"
#476000
0"
#477000
b1000111 &
1"
#478000
0"
#479000
b1000111 '
1"
#480000
0"
#481000
b1001000 &
1"
#482000
0"
#483000
b1001000 '
1"
#484000
0"
#485000
b1001001 &
1"
#486000
0"
#487000
b1001001 '
1"
#488000
0"
#489000
b1001010 &
1"
#490000
0"
#491000
b1001010 '
1"
#492000
0"
#493000
b1001011 &
1"
#494000
0"
#495000
b1001011 '
1"
#496000
0"
#497000
b1001100 &
1"
#498000
0"
#499000
b1001100 '
1"
#500000
0"
#501000
b1001101 &
1"
#502000
0"
#503000
b1001101 '
1"
#504000
0"
#505000
b1001110 &
1"
#506000
0"
#507000
b1001110 '
1"
#508000
0"
#509000
b1001111 &
1"
#510000
0"
#511000
b1001111 '
1"
#512000
0"
#513000
b1010000 &
1"
#514000
0"
#515000
b1010000 '
1"
#516000
0"
#517000
b1010001 &
1"
#518000
0"
#519000
b1010001 '
1"
#520000
0"
#521000
b1010010 &
1"
#522000
0"
#523000
b1010010 '
1"
#524000
0"
#525000
b1010011 &
1"
#526000
0"
#527000
b1010011 '
1"
#528000
0"
#529000
b1010100 &
1"
#530000
0"
#531000
b1010100 '
1"
#532000
0"
#533000
b1010101 &
1"
#534000
0"
#535000
b1010101 '
1"
#536000
0"
#537000
b1010110 &
1"
#538000
0"
#539000
b1010110 '
1"
#540000
0"
#541000
b1010111 &
1"
#542000
0"
#543000
b1010111 '
1"
#544000
0"
#545000
b1011000 &
1"
#546000
0"
#547000
b1011000 '
1"
#548000
0"
#549000
b1011001 &
1"
#550000
0"
#551000
b1011001 '
1"
#552000
0"
#553000
b1011010 &
1"
#554000
0"
#555000
b1011010 '
1"
#556000
0"
#557000
b1011011 &
1"
#558000
0"
#559000
b1011011 '
1"
#560000
0"
#561000
b1011100 &
1"
#562000
0"
#563000
b1011100 '
1"
#564000
0"
#565000
b1011101 &
1"
#566000
0"
#567000
b1011101 '
1"
#568000
0"
#569000
b1011110 &
1"
#570000
0"
#571000
b1011110 '
1"
#572000
0"
#573000
b1011111 &
1"
#574000
0"
#575000
b1011111 '
1"
#576000
0"
#577000
b1100000 &
1"
#578000
0"
#579000
b1100000 '
1"
#580000
0"
#581000
b1100001 &
1"
#582000
0"
#583000
b1100001 '
1"
#584000
0"
#585000
b1100010 &
1"
#586000
0"
#587000
b1100010 '
1"
#588000
0"
#589000
b1100011 &
1"
#590000
0"
#591000
b1100011 '
1"
#592000
0"
#593000
b1100100 &
1"
#594000
0"
#595000
b1100100 '
1"
#596000
0"
#597000
b1100101 &
1"
#598000
0"
#599000
b1100101 '
1"
#600000
0"
#601000
b1100110 &
1"
#602000
0"
#603000
b1100110 '
1"
#604000
0"
#605000
b1100111 &
1"
#606000
0"
#607000
b1100111 '
1"
#608000
0"
#609000
b1101000 &
1"
#610000
0"
#611000
b1101000 '
1"
#612000
0"
#613000
b1101001 &
1"
#614000
0"
#615000
b1101001 '
1"
#616000
0"
#617000
b1101010 &
1"
#618000
0"
#619000
b1101010 '
1"
#620000
0"
#621000
b1101011 &
1"
#622000
0"
#623000
b1101011 '
1"
#624000
0"
#625000
b1101100 &
1"
#626000
0"
#627000
b1101100 '
1"
#628000
0"
#629000
b1101101 &
1"
#630000
0"
#631000
b1101101 '
1"
#632000
0"
#633000
b1101110 &
1"
#634000
0"
#635000
b1101110 '
1"
#636000
0"
#637000
b1101111 &
1"
#638000
0"
#639000
b1101111 '
1"
#640000
0"
#641000
b1110000 &
1"
#642000
0"
#643000
b1110000 '
1"
#644000
0"
#645000
b1110001 &
1"
#646000
0"
#647000
b1110001 '
1"
#648000
0"
#649000
b1110010 &
1"
#650000
0"
#651000
b1110010 '
1"
#652000
0"
#653000
b1110011 &
1"
#654000
0"
#655000
b1110011 '
1"
#656000
0"
#657000
b1110100 &
1"
#658000
0"
#659000
b1110100 '
1"
#660000
0"
#661000
b1110101 &
1"
#662000
0"
#663000
b1110101 '
1"
#664000
0"
#665000
b1110110 &
1"
#666000
0"
#667000
b1110110 '
1"
#668000
0"
#669000
b1110111 &
1"
#670000
0"
#671000
b1110111 '
1"
#672000
0"
#673000
b1111000 &
1"
#674000
0"
#675000
b1111000 '
1"
#676000
0"
#677000
b1111001 &
1"
#678000
0"
#679000
b1111001 '
1"
#680000
0"
#681000
b1111010 &
1"
#682000
0"
#683000
b1111010 '
1"
#684000
0"
#685000
b1111011 &
1"
#686000
0"
#687000
b1111011 '
1"
#688000
0"
#689000
b1111100 &
1"
#690000
0"
#691000
b1111100 '
1"
#692000
0"
#693000
b1111101 &
1"
#694000
0"
#695000
b1111101 '
1"
#696000
0"
#697000
b1111110 &
1"
#698000
0"
#699000
b1111110 '
1"
#700000
0"
#701000
b1111111 &
1"
#702000
0"
#703000
b1111111 '
1"
#704000
0"
#705000
b10000000 &
1"
#706000
0"
#707000
b10000000 '
1"
#708000
0"
#709000
b10000001 &
1"
#710000
0"
#711000
b10000001 '
1"
#712000
0"
#713000
b10000010 &
1"
#714000
0"
#715000
b10000010 '
1"
#716000
0"
#717000
b10000011 &
1"
#718000
0"
#719000
b10000011 '
1"
#720000
0"
#721000
b10000100 &
1"
#722000
0"
#723000
b10000100 '
1"
#724000
0"
#725000
b10000101 &
1"
#726000
0"
#727000
b10000101 '
1"
#728000
0"
#729000
b10000110 &
1"
#730000
0"
#731000
b10000110 '
1"
#732000
0"
#733000
b10000111 &
1"
#734000
0"
#735000
b10000111 '
1"
#736000
0"
#737000
b10001000 &
1"
#738000
0"
#739000
b10001000 '
1"
#740000
0"
#741000
b10001001 &
1"
#742000
0"
#743000
b10001001 '
1"
#744000
0"
#745000
b10001010 &
1"
#746000
0"
#747000
b10001010 '
1"
#748000
0"
#749000
b10001011 &
1"
#750000
0"
#751000
b10001011 '
1"
#752000
0"
#753000
b10001100 &
1"
#754000
0"
#755000
b10001100 '
1"
#756000
0"
#757000
b10001101 &
1"
#758000
0"
#759000
b10001101 '
1"
#760000
0"
#761000
b10001110 &
1"
#762000
0"
#763000
b10001110 '
1"
#764000
0"
#765000
b10001111 &
1"
#766000
0"
#767000
b10001111 '
1"
#768000
0"
#769000
b10010000 &
1"
#770000
0"
#771000
b10010000 '
1"
#772000
0"
#773000
b10010001 &
1"
#774000
0"
#775000
b10010001 '
1"
#776000
0"
#777000
b10010010 &
1"
#778000
0"
#779000
b10010010 '
1"
#780000
0"
#781000
b10010011 &
1"
#782000
0"
#783000
b10010011 '
1"
#784000
0"
#785000
b10010100 &
1"
#786000
0"
#787000
b10010100 '
1"
#788000
0"
#789000
b10010101 &
1"
#790000
0"
#791000
b10010101 '
1"
#792000
0"
#793000
b10010110 &
1"
#794000
0"
#795000
b10010110 '
1"
#796000
0"
#797000
b10010111 &
1"
#798000
0"
#799000
b10010111 '
1"
#800000
0"
#801000
b10011000 &
1"
#802000
0"
#803000
b10011000 '
1"
#804000
0"
#805000
b10011001 &
1"
#806000
0"
#807000
b10011001 '
1"
#808000
0"
#809000
b10011010 &
1"
#810000
0"
#811000
b10011010 '
1"
#812000
0"
#813000
b10011011 &
1"
#814000
0"
#815000
b10011011 '
1"
#816000
0"
#817000
b10011100 &
1"
#818000
0"
#819000
b10011100 '
1"
#820000
0"
#821000
b10011101 &
1"
#822000
0"
#823000
b10011101 '
1"
#824000
0"
#825000
b10011110 &
1"
#826000
0"
#827000
b10011110 '
1"
#828000
0"
#829000
b10011111 &
1"
#830000
0"
#831000
b10011111 '
1"
#832000
0"
#833000
b10100000 &
1"
#834000
0"
#835000
b10100000 '
1"
#836000
0"
#837000
b10100001 &
1"
#838000
0"
#839000
b10100001 '
1"
#840000
0"
#841000
b10100010 &
1"
#842000
0"
#843000
b10100010 '
1"
#844000
0"
#845000
b10100011 &
1"
#846000
0"
#847000
b10100011 '
1"
#848000
0"
#849000
b10100100 &
1"
#850000
0"
#851000
b10100100 '
1"
#852000
0"
#853000
b10100101 &
1"
#854000
0"
#855000
b10100101 '
1"
#856000
0"
#857000
b10100110 &
1"
#858000
0"
#859000
b10100110 '
1"
#860000
0"
#861000
b10100111 &
1"
#862000
0"
#863000
b10100111 '
1"
#864000
0"
#865000
b10101000 &
1"
#866000
0"
#867000
b10101000 '
1"
#868000
0"
#869000
b10101001 &
1"
#870000
0"
#871000
b10101001 '
1"
#872000
0"
#873000
b10101010 &
1"
#874000
0"
#875000
b10101010 '
1"
#876000
0"
#877000
b10101011 &
1"
#878000
0"
#879000
b10101011 '
1"
#880000
0"
#881000
b10101100 &
1"
#882000
0"
#883000
b10101100 '
1"
#884000
0"
#885000
b10101101 &
1"
#886000
0"
#887000
b10101101 '
1"
#888000
0"
#889000
b10101110 &
1"
#890000
0"
#891000
b10101110 '
1"
#892000
0"
#893000
b10101111 &
1"
#894000
0"
#895000
b10101111 '
1"
#896000
0"
#897000
b10110000 &
1"
#898000
0"
#899000
b10110000 '
1"
#900000
0"
#901000
b10110001 &
1"
#902000
0"
#903000
b10110001 '
1"
#904000
0"
#905000
b10110010 &
1"
#906000
0"
#907000
b10110010 '
1"
#908000
0"
#909000
b10110011 &
1"
#910000
0"
#911000
b10110011 '
1"
#912000
0"
#913000
b10110100 &
1"
#914000
0"
#915000
b10110100 '
1"
#916000
0"
#917000
b10110101 &
1"
#918000
0"
#919000
b10110101 '
1"
#920000
0"
#921000
b10110110 &
1"
#922000
0"
#923000
b10110110 '
1"
#924000
0"
#925000
b10110111 &
1"
#926000
0"
#927000
b10110111 '
1"
#928000
0"
#929000
b10111000 &
1"
#930000
0"
#931000
b10111000 '
1"
#932000
0"
#933000
b10111001 &
1"
#934000
0"
#935000
b10111001 '
1"
#936000
0"
#937000
b10111010 &
1"
#938000
0"
#939000
b10111010 '
1"
#940000
0"
#941000
b10111011 &
1"
#942000
0"
#943000
b10111011 '
1"
#944000
0"
#945000
b10111100 &
1"
#946000
0"
#947000
b10111100 '
1"
#948000
0"
#949000
b10111101 &
1"
#950000
0"
#951000
b10111101 '
1"
#952000
0"
#953000
b10111110 &
1"
#954000
0"
#955000
b10111110 '
1"
#956000
0"
#957000
b10111111 &
1"
#958000
0"
#959000
b10111111 '
1"
#960000
0"
#961000
b11000000 &
1"
#962000
0"
#963000
b11000000 '
1"
#964000
0"
#965000
b11000001 &
1"
#966000
0"
#967000
b11000001 '
1"
#968000
0"
#969000
b11000010 &
1"
#970000
0"
#971000
b11000010 '
1"
#972000
0"
#973000
b11000011 &
1"
#974000
0"
#975000
b11000011 '
1"
#976000
0"
#977000
b11000100 &
1"
#978000
0"
#979000
b11000100 '
1"
#980000
0"
#981000
b11000101 &
1"
#982000
0"
#983000
b11000101 '
1"
#984000
0"
#985000
b11000110 &
1"
#986000
0"
#987000
b11000110 '
1"
#988000
0"
#989000
b11000111 &
1"
#990000
0"
#991000
b11000111 '
1"
#992000
0"
#993000
b11001000 &
1"
#994000
0"
#995000
b11001000 '
1"
#996000
0"
#997000
b11001001 &
1"
#998000
0"
#999000
b11001001 '
1"
#1000000
0"
#1001000
b11001010 &
1"
#1002000
0"
#1003000
b11001010 '
1"
#1004000
0"
#1005000
b11001011 &
1"
#1006000
0"
#1007000
b11001011 '
1"
#1008000
0"
#1009000
b11001100 &
1"
#1010000
0"
#1011000
b11001100 '
1"
#1012000
0"
#1013000
b11001101 &
1"
#1014000
0"
#1015000
b11001101 '
1"
#1016000
0"
#1017000
b11001110 &
1"
#1018000
0"
#1019000
b11001110 '
1"
#1020000
0"
#1021000
b11001111 &
1"
#1022000
0"
#1023000
b11001111 '
1"
#1024000
0"
#1025000
b11010000 &
1"
#1026000
0"
#1027000
b11010000 '
1"
#1028000
0"
#1029000
b11010001 &
1"
#1030000
0"
#1031000
b11010001 '
1"
#1032000
0"
#1033000
b11010010 &
1"
#1034000
0"
#1035000
b11010010 '
1"
#1036000
0"
#1037000
b11010011 &
1"
#1038000
0"
#1039000
b11010011 '
1"
#1040000
0"
#1041000
b11010100 &
1"
#1042000
0"
#1043000
b11010100 '
1"
#1044000
0"
#1045000
b11010101 &
1"
#1046000
0"
#1047000
b11010101 '
1"
#1048000
0"
#1049000
b11010110 &
1"
#1050000
0"
#1051000
b11010110 '
1"
#1052000
0"
#1053000
b11010111 &
1"
#1054000
0"
#1055000
b11010111 '
1"
#1056000
0"
#1057000
b11011000 &
1"
#1058000
0"
#1059000
b11011000 '
1"
#1060000
0"
#1061000
b11011001 &
1"
#1062000
0"
#1063000
b11011001 '
1"
#1064000
0"
#1065000
b11011010 &
1"
#1066000
0"
#1067000
b11011010 '
1"
#1068000
0"
#1069000
b11011011 &
1"
#1070000
0"
#1071000
b11011011 '
1"
#1072000
0"
#1073000
b11011100 &
1"
#1074000
0"
#1075000
b11011100 '
1"
#1076000
0"
#1077000
b11011101 &
1"
#1078000
0"
#1079000
b11011101 '
1"
#1080000
0"
#1081000
b11011110 &
1"
#1082000
0"
#1083000
b11011110 '
1"
#1084000
0"
#1085000
b11011111 &
1"
#1086000
0"
#1087000
b11011111 '
1"
#1088000
0"
#1089000
b11100000 &
1"
#1090000
0"
#1091000
b11100000 '
1"
#1092000
0"
#1093000
b11100001 &
1"
#1094000
0"
#1095000
b11100001 '
1"
#1096000
0"
#1097000
b11100010 &
1"
#1098000
0"
#1099000
b11100010 '
1"
#1100000
0"
#1101000
b11100011 &
1"
#1102000
0"
#1103000
b11100011 '
1"
#1104000
0"
#1105000
b11100100 &
1"
#1106000
0"
#1107000
b11100100 '
1"
#1108000
0"
#1109000
b11100101 &
1"
#1110000
0"
#1111000
b11100101 '
1"
#1112000
0"
#1113000
b11100110 &
1"
#1114000
0"
#1115000
b11100110 '
1"
#1116000
0"
#1117000
b11100111 &
1"
#1118000
0"
#1119000
b11100111 '
1"
#1120000
0"
#1121000
b11101000 &
1"
#1122000
0"
#1123000
b11101000 '
1"
#1124000
0"
#1125000
b11101001 &
1"
#1126000
0"
#1127000
b11101001 '
1"
#1128000
0"
#1129000
b11101010 &
1"
#1130000
0"
#1131000
b11101010 '
1"
#1132000
0"
#1133000
b11101011 &
1"
#1134000
0"
#1135000
b11101011 '
1"
#1136000
0"
#1137000
b11101100 &
1"
#1138000
0"
#1139000
b11101100 '
1"
#1140000
0"
#1141000
b11101101 &
1"
#1142000
0"
#1143000
b11101101 '
1"
#1144000
0"
#1145000
b11101110 &
1"
#1146000
0"
#1147000
b11101110 '
1"
#1148000
0"
#1149000
b11101111 &
1"
#1150000
0"
#1151000
b11101111 '
1"
#1152000
0"
#1153000
b11110000 &
1"
#1154000
0"
#1155000
b11110000 '
1"
#1156000
0"
#1157000
b11110001 &
1"
#1158000
0"
#1159000
b11110001 '
1"
#1160000
0"
#1161000
b11110010 &
1"
#1162000
0"
#1163000
b11110010 '
1"
#1164000
0"
#1165000
b11110011 &
1"
#1166000
0"
#1167000
b11110011 '
1"
#1168000
0"
#1169000
b11110100 &
1"
#1170000
0"
#1171000
b11110100 '
1"
#1172000
0"
#1173000
b11110101 &
1"
#1174000
0"
#1175000
b11110101 '
1"
#1176000
0"
#1177000
b11110110 &
1"
#1178000
0"
#1179000
b11110110 '
1"
#1180000
0"
#1181000
b11110111 &
1"
#1182000
0"
#1183000
b11110111 '
1"
#1184000
0"
#1185000
b11111000 &
1"
#1186000
0"
#1187000
b11111000 '
1"
#1188000
0"
#1189000
b11111001 &
1"
#1190000
0"
#1191000
b11111001 '
1"
#1192000
0"
#1193000
b11111010 &
1"
#1194000
0"
#1195000
b11111010 '
1"
#1196000
0"
#1197000
b11111011 &
1"
#1198000
0"
#1199000
b11111011 '
1"
#1200000
0"
#1201000
b11111100 &
1"
#1202000
0"
#1203000
b11111100 '
1"
#1204000
0"
#1205000
b11111101 &
1"
#1206000
0"
#1207000
b11111101 '
1"
#1208000
0"
#1209000
b11111110 &
1"
#1210000
0"
#1211000
b11111110 '
1"
#1212000
0"
#1213000
b11111111 &
1"
#1214000
0"
#1215000
b11111111 '
1"
#1216000
0"
#1217000
b100000000 &
1"
#1218000
0"
#1219000
b100000000 '
1"
#1220000
0"
#1221000
b0 !
0(
b100000001 &
1"
#1222000
0"
#1223000
b100000001 '
1"
#1224000
0"
#1225000
b100000010 &
1"
#1226000
0"
#1227000
b100000010 '
1"
#1228000
0"
#1229000
b100000011 &
1"
#1230000
0"
#1231000
b100000011 '
1"
#1232000
0"
#1233000
b100000100 &
1"
#1234000
0"
#1235000
b100000100 '
1"
#1236000
0"
#1237000
b100000101 &
1"
#1238000
0"
#1239000
b100000101 '
1"
#1240000
0"
#1241000
b100000110 &
1"
#1242000
0"
#1243000
b100000110 '
1"
#1244000
0"
#1245000
b100000111 &
1"
#1246000
0"
#1247000
b100000111 '
1"
#1248000
0"
#1249000
b100001000 &
1"
#1250000
0"
#1251000
b100001000 '
1"
#1252000
0"
#1253000
b100001001 &
1"
#1254000
0"
#1255000
b100001001 '
1"
#1256000
0"
#1257000
b100001010 &
1"
#1258000
0"
#1259000
b100001010 '
1"
#1260000
0"
#1261000
b100001011 &
1"
#1262000
0"
#1263000
b100001011 '
1"
#1264000
0"
#1265000
b100001100 &
1"
#1266000
0"
#1267000
b100001100 '
1"
#1268000
0"
#1269000
b100001101 &
1"
#1270000
0"
#1271000
b100001101 '
1"
#1272000
0"
#1273000
b100001110 &
1"
#1274000
0"
#1275000
b100001110 '
1"
#1276000
0"
#1277000
b100001111 &
1"
#1278000
0"
#1279000
b100001111 '
1"
#1280000
0"
#1281000
b100010000 &
1"
#1282000
0"
#1283000
b100010000 '
1"
#1284000
0"
#1285000
b100010001 &
1"
#1286000
0"
#1287000
b100010001 '
1"
#1288000
0"
#1289000
b100010010 &
1"
#1290000
0"
#1291000
b100010010 '
1"
#1292000
0"
#1293000
b100010011 &
1"
#1294000
0"
#1295000
b100010011 '
1"
#1296000
0"
#1297000
b100010100 &
1"
#1298000
0"
#1299000
b100010100 '
1"
#1300000
0"
#1301000
b100010101 &
1"
#1302000
0"
#1303000
b100010101 '
1"
#1304000
0"
#1305000
b100010110 &
1"
#1306000
0"
#1307000
b100010110 '
1"
#1308000
0"
#1309000
b100010111 &
1"
#1310000
0"
#1311000
b100010111 '
1"
#1312000
0"
#1313000
b100011000 &
1"
#1314000
0"
#1315000
b100011000 '
1"
#1316000
0"
#1317000
b100011001 &
1"
#1318000
0"
#1319000
b100011001 '
1"
#1320000
0"
#1321000
b100011010 &
1"
#1322000
0"
#1323000
b100011010 '
1"
#1324000
0"
#1325000
b100011011 &
1"
#1326000
0"
#1327000
b100011011 '
1"
#1328000
0"
#1329000
b100011100 &
1"
#1330000
0"
#1331000
b100011100 '
1"
#1332000
0"
#1333000
b100011101 &
1"
#1334000
0"
#1335000
b100011101 '
1"
#1336000
0"
#1337000
b100011110 &
1"
#1338000
0"
#1339000
b100011110 '
1"
#1340000
0"
#1341000
b100011111 &
1"
#1342000
0"
#1343000
b100011111 '
1"
#1344000
0"
#1345000
b100100000 &
1"
#1346000
0"
#1347000
b100100000 '
1"
#1348000
0"
#1349000
b100100001 &
1"
#1350000
0"
#1351000
b100100001 '
1"
#1352000
0"
#1353000
b100100010 &
1"
#1354000
0"
#1355000
b100100010 '
1"
#1356000
0"
#1357000
b100100011 &
1"
#1358000
0"
#1359000
b100100011 '
1"
#1360000
0"
#1361000
b100100100 &
1"
#1362000
0"
#1363000
b100100100 '
1"
#1364000
0"
#1365000
b100100101 &
1"
#1366000
0"
#1367000
b100100101 '
1"
#1368000
0"
#1369000
b100100110 &
1"
#1370000
0"
#1371000
b100100110 '
1"
#1372000
0"
#1373000
b100100111 &
1"
#1374000
0"
#1375000
b100100111 '
1"
#1376000
0"
